threadwrapper/__init__.py
threadwrapper/_async.py
threadwrapper/core.py
threadwrapper/__metadata__/DISCLIAIMER.md
threadwrapper/__metadata__/LICENSE
threadwrapper/__metadata__/README.md
threadwrapper/__metadata__/__init__.py
threadwrapper/__metadata__/requirements.txt
threadwrapper-0.13.1.dist-info/METADATA
threadwrapper-0.13.1.dist-info/WHEEL
threadwrapper-0.13.1.dist-info/top_level.txt
threadwrapper-0.13.1.dist-info/RECORD
