Metadata-Version: 2.1
Name: threadwrapper
Version: 0.13.1
Summary: Gather results from multiple threads seamlessly.
Home-page: http://code.foxe6.kozow.com/threadwrapper/
Author: f̣ộx̣ệ6
Author-email: foxe6@pm.me
License: AGPL-3.0
Project-URL: Sourcecode, http://code.foxe6.kozow.com/threadwrapper.zip
Project-URL: Documentation, http://code.foxe6.kozow.com/threadwrapper/docs/
Project-URL: Example, http://code.foxe6.kozow.com/threadwrapper/test/
Project-URL: Funding, https://paypal.me/foxe6
Project-URL: Say Thanks!, https://saythanks.io/to/foxe6
Keywords: thread wrapper asyncio
Platform: UNKNOWN
Classifier: Programming Language :: Python :: 3.9
Classifier: Topic :: Utilities
Classifier: Natural Language :: English
Classifier: Intended Audience :: Developers
Classifier: License :: OSI Approved :: GNU Affero General Public License v3
Classifier: Operating System :: MacOS
Classifier: Operating System :: POSIX
Classifier: Operating System :: Microsoft :: Windows :: Windows 10
Classifier: Development Status :: 5 - Production/Stable
Requires-Python: >=3.5
Requires-Dist: omnitools (>=0.0.1)
